{
    "images":[
        {
            "id": "1",
            "country": "France",
            "url": "https://tk3d.pre-tk3dapi.com/activation/images/november.jpg",
            "link": "http://mobilemediacontent.com/"
        },
        {
            "id": "2",
            "country": "Germany",
            "url": "https://tk3d.pre-tk3dapi.com/activation/images/caixabank.png",
            "link": "https://www.upf.edu/",
            "data":{
                "day":"15-6-2020",
                "time":"13:40:00",
                "duration": "10 s"
            }
        },
        {
            "id": "3",
            "country": "Canada",
            "url": "https://tk3d.pre-tk3dapi.com/activation/images/caixabank_white.jpg",
            "link": "http://mobilemediacontent.com/",
            "data":{
                "day":"15-6-2020",
                "time":"13:43:00",
                "duration": "10 s"
            }
        },
        {
            "id": "4",
            "country": "Netherlands",
            "url": "https://tk3d.pre-tk3dapi.com/activation/images/gasnatural_black.jpg",
            "link": "https://3ddigitalvenue.com/",
            "data":{
                "day":"15-6-2020",
                "time":"13:46:00",
                "duration": "10 s"
            }
        },
        {
            "id": "5",
            "country": "Norway",
            "url": "https://tk3d.pre-tk3dapi.com/activation/images/gasnatural_white.jpg",
            "link": "https://www.upf.edu/",
            "vip":"true"
        },
        {
            "id": "6",
            "country": "USA",
            "url": "https://tk3d.pre-tk3dapi.com/activation/images/gasnaturalfenosa.png",
            "link": "http://mobilemediacontent.com/",
            "data":{
                "day":"15-6-2020",
                "time":"13:49:00",
                "duration": "10 s"
            }
        }
    ],
    "videos":[
        {
            "id": "99",
            "country": "France",
            "url": "https://tk3d.pre-tk3dapi.com/activation/videos/masriera-480.mp4",
            "link": "http://mobilemediacontent.com/"
        },
        {
            "id": "98",
            "country": "Germany",
            "url": "https://tk3d.pre-tk3dapi.com/activation/videos/masriera-720.mp4",
            "link": "https://3ddigitalvenue.com/"
        },
        {
            "id": "97",
            "country": "USA",
            "url": "https://tk3d.pre-tk3dapi.com/activation/videos/sample-480.mp4",
            "link": "https://www.upf.edu/"
        },
        {
            "id": "96",
            "country": "Spain",
            "url": "https://tk3d.pre-tk3dapi.com/activation/videos/sample-720.mp4",
            "link": "http://mobilemediacontent.com/"
        }
    ]
}